<?xml version='1.0' encoding='ISO-8859-1' ?>
<!-- $Revision: 1.1.6.6 $ $Date: 2004/04/26 23:23:12 $ -->

<toc version="1.0">

<tocitem target="fixedpoint_product_page.html" image="$toolbox/matlab/icons/book_mat.gif">Fixed-Point Toolbox

<tocitem target="getting_.html" image="$toolbox/matlab/icons/greencircleicon.gif">Getting Started
    <tocitem target="getting2.html#6363">What Is the Fixed-Point Toolbox?
        <tocitem target="getting2.html#6365">Features</tocitem>
    </tocitem>
    <tocitem target="getting3.html#6316">Getting Help
        <tocitem target="getting3.html#6162">Getting Help in this Document</tocitem>
        <tocitem target="getting3.html#6167">Getting Help at the MATLAB Command Line</tocitem>
    </tocitem>
    <tocitem target="getting4.html#6700">Display Settings</tocitem>
    <tocitem target="getting5.html#6878">Demos</tocitem>
</tocitem>
<tocitem target="fixedpoint_example_index.html" image="$toolbox/matlab/icons/demoicon.gif">Examples</tocitem>
<tocitem target="fixed-po.html" image="$toolbox/matlab/icons/pagesicon.gif">Fixed-Point Concepts
    <tocitem target="fixed-p2.html#6312">Fixed-Point Data Types</tocitem>
    <tocitem target="fixed-p3.html#6389">Scaling</tocitem>
    <tocitem target="fixed-p4.html#6415">Precision and Range
        <tocitem target="fixed-p4.html#6417">Range</tocitem>
        <tocitem target="fixed-p5.html#6478">Precision</tocitem>
    </tocitem>
    <tocitem target="fixed-p6.html#6488">Arithmetic Operations
        <tocitem target="fixed-p6.html#6512">Modulo Arithmetic</tocitem>
        <tocitem target="fixed-p7.html#6585">Two's Complement</tocitem>
        <tocitem target="fixed-p8.html#6609">Addition and Subtraction</tocitem>
        <tocitem target="fixed-p9.html#8588">Multiplication</tocitem>
        <tocitem target="fixed-10.html#9063">Casts</tocitem>
    </tocitem>
    <tocitem target="fixed11a.html#9736">fi Objects Compared to C Integer Data Types
        <tocitem target="fixed12a.html#9742">Integer Data Types</tocitem>
        <tocitem target="fixed13a.html#9748">Unary Conversions</tocitem>
        <tocitem target="fixed14a.html#15366">Binary Conversions</tocitem>
        <tocitem target="fixed15a.html#9750">Overflow Handling</tocitem>
    </tocitem>
</tocitem>
<tocitem target="workinga.html" image="$toolbox/matlab/icons/pagesicon.gif">Working with fi Objects
    <tocitem target="workin2a.html#6033">Constructing fi Objects
        <tocitem target="workin3a.html#6235">Examples of Constructing fi Objects</tocitem>
    </tocitem>
    <tocitem target="workin4a.html#6048">fi Object Properties
        <tocitem target="workin4a.html#9402">Data Properties</tocitem>
        <tocitem target="workin4a.html#9407">fimath Properties</tocitem>
        <tocitem target="workin4a.html#9408">numerictype Properties</tocitem>
        <tocitem target="workin5a.html#6629">Setting Fixed-Point Properties at Object Creation</tocitem>
        <tocitem target="workin6a.html#6829">Using Direct Property Referencing with fi</tocitem>
    </tocitem>
    <tocitem target="workin7a.html#6063">fi Object Functions</tocitem>
</tocitem>
<tocitem target="workingb.html" image="$toolbox/matlab/icons/pagesicon.gif">Working with fimath Objects
    <tocitem target="workin2b.html#7588">Constructing fimath Objects</tocitem>
    <tocitem target="workin3b.html#5978">fimath Object Properties
        <tocitem target="workin4b.html#6147">Setting fimath Properties at Object Creation</tocitem>
        <tocitem target="workin5c.html#6172">Using Direct Property Referencing with fimath</tocitem>
    </tocitem>
    <tocitem target="workin6c.html#6860">Using fimath Objects to Perform Fixed-Point Arithmetic</tocitem>
    <tocitem target="workin7c.html#7200">Using fimath to Share Arithmetic Rules</tocitem>
    <tocitem target="working8.html#6060">fimath Object Functions</tocitem>
</tocitem>
<tocitem target="working_.html" image="$toolbox/matlab/icons/pagesicon.gif">Working with fipref Objects
    <tocitem target="working2.html#5937">Constructing fipref Objects</tocitem>
    <tocitem target="working3.html#6241">fipref Object Properties
        <tocitem target="working4.html#6482">Setting fipref Properties at Object Creation</tocitem>
        <tocitem target="working5.html#6488">Using Direct Property Referencing with fipref</tocitem>
    </tocitem>
    <tocitem target="working6.html#6401">Using fipref Objects to Set Display Preferences</tocitem>
    <tocitem target="working7.html#6403">fipref Object Functions</tocitem>
</tocitem>
<tocitem target="workingd.html" image="$toolbox/matlab/icons/pagesicon.gif">Working with numerictype Objects
    <tocitem target="workin2d.html#6033">Constructing numerictype Objects</tocitem>
    <tocitem target="workin3d.html#6048">numerictype Object Properties
        <tocitem target="workin4d.html#6629">Setting numerictype Properties at Object Creation</tocitem>
        <tocitem target="workin5d.html#10754">Using Direct Property Referencing with numerictype objects</tocitem>
    </tocitem>
    <tocitem target="workin6d.html#11188">The numerictype Structure
        <tocitem target="workin6d.html#12616">Properties That Affect the Slope</tocitem>
        <tocitem target="workin6d.html#12634">Stored Integer Value and Real World Value</tocitem>
    </tocitem>
    <tocitem target="workin7d.html#10909">Using numerictype Objects to Share Data Type and Scaling Settings</tocitem>
    <tocitem target="workin8a.html#12462">numerictype Object Functions</tocitem>
</tocitem>
<tocitem target="workingc.html" image="$toolbox/matlab/icons/pagesicon.gif">Working with quantizer Objects
    <tocitem target="workin2c.html#10637">Constructing quantizer Objects</tocitem>
    <tocitem target="workin3c.html#8765">quantizer Object Properties
        <tocitem target="workin4c.html#10840">Settable quantizer Object Properties</tocitem>
        <tocitem target="workin5b.html#10661">Read-Only quantizer Object Properties</tocitem>
    </tocitem>
    <tocitem target="workin6b.html#10671">Quantizing Data with quantizer Objects</tocitem>
    <tocitem target="workin7b.html#10663">Transformations for Quantized Data</tocitem>
    <tocitem target="workin8b.html#10682">quantizer Object Functions</tocitem>
</tocitem>
<tocitem target="interope.html" image="$toolbox/matlab/icons/pagesicon.gif">Interoperability with Other Products
    <tocitem target="interop2.html#5937">Using fi Objects with Simulink
        <tocitem target="interop2.html#6113">Reading Fixed-Point Data from the Workspace</tocitem>
        <tocitem target="interop2.html#7242">Writing Fixed-Point Data to the Workspace</tocitem>
        <tocitem target="interop2.html#8179">Logging Fixed-Point Signals</tocitem>
        <tocitem target="interop2.html#8131">Accessing Fixed-Point Block Data During Simulation</tocitem>
    </tocitem>
    <tocitem target="interop3.html#6059">Using fi Objects with Signal Processing Blockset
        <tocitem target="interop3.html#6164">Reading Fixed-Point Signals from the Workspace</tocitem>
        <tocitem target="interop3.html#6166">Writing Fixed-Point Signals to the Workspace</tocitem>
    </tocitem>
    <tocitem target="interop4.html#6288">Using fi Objects with Filter Design Toolbox</tocitem>
</tocitem>
<tocitem target="properti.html" image="$toolbox/matlab/icons/reficon.gif">Property Reference
    <tocitem target="propert2.html#31078">fi Object Properties
        <tocitem target="propert2.html#52258">bin</tocitem>
        <tocitem target="propert2.html#52145">data</tocitem>
        <tocitem target="propert2.html#52205">dec</tocitem>
        <tocitem target="propert2.html#52222">double</tocitem>
        <tocitem target="propert2.html#50390">fimath</tocitem>
        <tocitem target="propert2.html#52223">hex</tocitem>
        <tocitem target="propert2.html#48741">int</tocitem>
        <tocitem target="propert2.html#50731">NumericType</tocitem>
        <tocitem target="propert2.html#52224">oct</tocitem>
    </tocitem>
    <tocitem target="propert3.html#45283">fimath Object Properties
        <tocitem target="propert3.html#45288">CastBeforeSum</tocitem>
        <tocitem target="propert3.html#45481">MaxProductWordLength</tocitem>
        <tocitem target="propert3.html#50069">MaxSumWordLength</tocitem>
        <tocitem target="propert3.html#51769">OverflowMode</tocitem>
        <tocitem target="propert3.html#45473">ProductFractionLength</tocitem>
        <tocitem target="propert3.html#45464">ProductMode</tocitem>
        <tocitem target="propert3.html#45471">ProductWordLength</tocitem>
        <tocitem target="propert3.html#45350">RoundMode</tocitem>
        <tocitem target="propert3.html#45737">SumFractionLength</tocitem>
        <tocitem target="propert3.html#45497">SumMode</tocitem>
        <tocitem target="propert3.html#45501">SumWordLength</tocitem>
    </tocitem>
    <tocitem target="propert4.html#45682">fipref Object Properties
        <tocitem target="propert4.html#45703">FimathDisplay</tocitem>
        <tocitem target="propert4.html#45708">NumericTypeDisplay</tocitem>
        <tocitem target="propert4.html#45710">NumberDisplay</tocitem>
    </tocitem>
    <tocitem target="propert5.html#50087">numerictype Object Properties
        <tocitem target="propert5.html#50089">Bias</tocitem>
        <tocitem target="propert5.html#49237">DataType</tocitem>
        <tocitem target="propert5.html#50101">DataTypeMode</tocitem>
        <tocitem target="propert5.html#49279">FixedExponent</tocitem>
        <tocitem target="propert5.html#49309">FractionLength</tocitem>
        <tocitem target="propert5.html#49581">Scaling</tocitem>
        <tocitem target="propert5.html#49590">Signed</tocitem>
        <tocitem target="propert5.html#49597">Slope</tocitem>
        <tocitem target="propert5.html#51226">SlopeAdjustmentFactor</tocitem>
        <tocitem target="propert5.html#49610">WordLength</tocitem>
    </tocitem>
    <tocitem target="proper6a.html#46184">quantizer Object Properties
        <tocitem target="proper6a.html#47885">DataMode</tocitem>
        <tocitem target="proper6a.html#46409">Format</tocitem>
        <tocitem target="proper6a.html#46490">Max</tocitem>
        <tocitem target="proper6a.html#46496">Min</tocitem>
        <tocitem target="proper6a.html#46547">NOperations</tocitem>
        <tocitem target="proper6a.html#46556">NOverflows</tocitem>
        <tocitem target="proper6a.html#46563">NUnderflows</tocitem>
        <tocitem target="proper6a.html#46571">OverflowMode</tocitem>
        <tocitem target="proper6a.html#46591">RoundMode</tocitem>
    </tocitem>
</tocitem>
<tocitem target="func_by2.html" image="$toolbox/matlab/icons/reficon.gif">Functions -- Categorical List
    <tocitem target="func_by3.html#31852">Bitwise Functions</tocitem>
    <tocitem target="func_by4.html#26365">Constructor and Property Functions</tocitem>
    <tocitem target="func_by5.html#26460">Data Manipulation Functions</tocitem>
    <tocitem target="func_by6.html#21395">Data Type Functions</tocitem>
    <tocitem target="func_by7.html#28761">Data Quantizing Functions</tocitem>
    <tocitem target="func_by8.html#28742">Math Operation Functions</tocitem>
    <tocitem target="func_by9.html#23755">Matrix Manipulation Functions</tocitem>
    <tocitem target="func_b10.html#25330">Numerical Type Functions</tocitem>
    <tocitem target="func_b11.html#23800">One-Dimensional Plotting Functions</tocitem>
    <tocitem target="func_b12.html#28629">Radix Conversion Functions</tocitem>
    <tocitem target="func_b13.html#22442">Relational Operator Functions</tocitem>
    <tocitem target="func_b14.html#24112">Statistics Functions</tocitem>
    <tocitem target="func_b15.html#24052">Subscripted Assignment and Reference Functions</tocitem>
</tocitem>
<tocitem target="func_b16.html" image="$toolbox/matlab/icons/reficon.gif">fi Object Functions</tocitem>
<tocitem target="func_b17.html" image="$toolbox/matlab/icons/reficon.gif">fimath Object Functions</tocitem>
<tocitem target="func_b18.html" image="$toolbox/matlab/icons/reficon.gif">fipref Object Functions</tocitem>
<tocitem target="func_b19.html" image="$toolbox/matlab/icons/reficon.gif">numerictype Object Functions</tocitem>
<tocitem target="func_b20.html" image="$toolbox/matlab/icons/reficon.gif">quantizer Object Functions</tocitem>
<tocitem target="func_ref.html" image="$toolbox/matlab/icons/reficon.gif">Functions -- Alphabetical List</tocitem>
<tocitem target="glossary.html" image="$toolbox/matlab/icons/reficon.gif">Glossary</tocitem>


<tocitem target="rn/fixedpoint.html" image="$toolbox/matlab/icons/notesicon.gif">Release Notes

<tocitem target="rn/fixedpoint14_1-0.html">Fixed-Point Toolbox 1.0 Release Notes
    <tocitem target="rn/fixedpoint14_1-0.html#7373">Introduction to the Fixed-Point Toolbox
        <tocitem target="rn/fixedpoint14_1-02.html#53361">Features</tocitem>
        <tocitem target="rn/fixedpoint14_1-03.html#53376">Getting Help</tocitem>
    </tocitem>
    <tocitem target="rn/fixedpoint14_1-04.html#53839">Known Software Problems
        <tocitem target="rn/fixedpoint14_1-04.html#53874">Bitwise Operators Might Return Wrong Answer for [Slope Bias] Signals</tocitem>
    </tocitem>
</tocitem>

</tocitem>
<tocitem target="fixedpoint_product_page.html" image="$toolbox/matlab/icons/pdficon.gif">Printable Documentation (PDF)</tocitem>
<tocitem target="http://www.mathworks.com/products/fixed/" image="$toolbox/matlab/icons/webicon.gif">Product Page (Web)</tocitem>

</tocitem>
</toc>
