<?xml version='1.0' encoding='ISO-8859-1' ?>
<!-- $Revision: 1.1.6.5 $ $Date: 2004/04/20 22:23:44 $ -->

<toc version="1.0">

<tocitem target="curvefit_product_page.html" image="$toolbox/matlab/icons/book_mat.gif">Curve Fitting Toolbox

<tocitem target="ch_start.html" image="$toolbox/matlab/icons/greencircleicon.gif">Getting Started
    <tocitem target="ch_start.html#38363">Getting Started with the Curve Fitting Toolbox
        <tocitem target="ch_star2.html#48342">What Is the Curve Fitting Toolbox?
            <tocitem target="ch_star3.html#48368">Differences Between the Curve Fitting Tool and Command-Line Environments</tocitem>
        </tocitem>
        <tocitem target="ch_star4.html#47076">Opening the Curve Fitting Tool</tocitem>
        <tocitem target="ch_star5.html#39504">Importing the Data</tocitem>
        <tocitem target="ch_star6.html#38981">Fitting the Data
            <tocitem target="ch_star6.html#41099">The Data Fitting Procedure</tocitem>
            <tocitem target="ch_star7.html#41634">Determining the Best Fit</tocitem>
            <tocitem target="ch_star8.html#42310">Saving the Fit Results</tocitem>
        </tocitem>
        <tocitem target="ch_star9.html#44211">Analyzing the Fit
            <tocitem target="ch_star9.html#40728">Saving the Analysis Results</tocitem>
        </tocitem>
        <tocitem target="ch_st10a.html#41511">Saving Your Work
            <tocitem target="ch_st10a.html#41983">Saving the Session</tocitem>
            <tocitem target="ch_st10a.html#42313">Generating an M-File</tocitem>
        </tocitem>
    </tocitem>
</tocitem>
<tocitem target="curvefit_example_index.html" image="$toolbox/matlab/icons/demoicon.gif">Examples</tocitem>
<tocitem target="ch_data.html" image="$toolbox/matlab/icons/pagesicon.gif">Importing, Viewing, and Preprocessing Data
    <tocitem target="ch_data2.html#39487">Importing Data Sets
        <tocitem target="ch_data3.html#43722">Example: Importing Data</tocitem>
    </tocitem>
    <tocitem target="ch_data4.html#50818">Viewing Data
        <tocitem target="ch_data4.html#60034">Viewing Data Graphically</tocitem>
        <tocitem target="ch_data4.html#60414">Viewing Data Numerically</tocitem>
    </tocitem>
    <tocitem target="ch_data5.html#59767">Smoothing Data
        <tocitem target="ch_data6.html#60810">Moving Average Filtering</tocitem>
        <tocitem target="ch_data7.html#59856">Lowess and Loess: Local Regression Smoothing</tocitem>
        <tocitem target="ch_data8.html#59924">Savitzky-Golay Filtering</tocitem>
        <tocitem target="ch_data9.html#59942">Example: Smoothing Data</tocitem>
    </tocitem>
    <tocitem target="ch_dat10.html#51068">Excluding and Sectioning Data
        <tocitem target="ch_dat11.html#40989">Marking Outliers</tocitem>
        <tocitem target="ch_dat12.html#48999">Sectioning</tocitem>
        <tocitem target="ch_dat13.html#52288">Example: Excluding and Sectioning Data</tocitem>
        <tocitem target="ch_dat14.html#58072">Example: Sectioning Periodic Data</tocitem>
    </tocitem>
    <tocitem target="ch_dat15.html#40602">Additional Preprocessing Steps
        <tocitem target="ch_dat15.html#53277">Transforming the Response Data</tocitem>
        <tocitem target="ch_dat16.html#42474">Removing Infs, NaNs, and Outliers</tocitem>
    </tocitem>
    <tocitem target="ch_dat17.html#50474">Selected Bibliography</tocitem>
</tocitem>
<tocitem target="ch_fitti.html" image="$toolbox/matlab/icons/pagesicon.gif">Fitting Data
    <tocitem target="ch_fitt2.html#66405">The Fitting Process</tocitem>
    <tocitem target="ch_fitt3.html#76041">Parametric Fitting
        <tocitem target="ch_fitt4.html#67985">Basic Assumptions About the Error</tocitem>
        <tocitem target="ch_fitt5.html#67660">The Least Squares Fitting Method</tocitem>
        <tocitem target="ch_fitt6.html#63727">Library Models</tocitem>
        <tocitem target="ch_fitt7.html#69221">Custom Equations</tocitem>
        <tocitem target="ch_fitt8.html#63698">Specifying Fit Options</tocitem>
        <tocitem target="ch_fitt9.html#57616">Evaluating the Goodness of Fit</tocitem>
        <tocitem target="ch_fit10.html#56967">Example: Rational Fit</tocitem>
        <tocitem target="ch_fit11.html#63139">Example: Fitting with Custom Equations</tocitem>
        <tocitem target="ch_fit12.html#57312">Example: Robust Fit</tocitem>
    </tocitem>
    <tocitem target="ch_fit13.html#38557">Nonparametric Fitting
        <tocitem target="ch_fit14.html#47600">Interpolants</tocitem>
        <tocitem target="ch_fit15.html#48072">Smoothing Spline</tocitem>
        <tocitem target="ch_fit16.html#83676">Example: Nonparametric Fit</tocitem>
    </tocitem>
    <tocitem target="ch_fi17a.html#38450">Selected Bibliography</tocitem>
</tocitem>
<tocitem target="ch_funct.html" image="$toolbox/matlab/icons/reficon.gif">Functions - By Category
    <tocitem target="ch_funct.html#36912">Fitting Data</tocitem>
    <tocitem target="ch_funct.html#33376">Getting Information and Help</tocitem>
    <tocitem target="ch_funct.html#33843">Getting and Setting Properties</tocitem>
    <tocitem target="ch_funct.html#33994">Preprocessing Data</tocitem>
    <tocitem target="ch_funct.html#35141">Postprocessing Data</tocitem>
    <tocitem target="ch_funct.html#35464">General Purpose</tocitem>
</tocitem>
<tocitem target="curvefia.html" image="$toolbox/matlab/icons/reficon.gif">Functions - Alphabetical List</tocitem>


<tocitem target="rn/curvefit.html" image="$toolbox/matlab/icons/notesicon.gif">Release Notes

<tocitem target="rn/curvefit13.html">Curve Fitting Toolbox 1.1 Release Notes
    <tocitem target="rn/curvefit13.html#7373">New Features
        <tocitem target="rn/curvefit13.html#52221">Exclude GUI</tocitem>
        <tocitem target="rn/curvefit13.html#52327">Viewing Data Numerically</tocitem>
    </tocitem>
    <tocitem target="rn/curvefit132.html#52258">Upgrading from an Earlier Release
        <tocitem target="rn/curvefit132.html#52388">Exclude GUI</tocitem>
        <tocitem target="rn/curvefit132.html#52390">Viewing Data Numerically</tocitem>
    </tocitem>
</tocitem>

</tocitem>
<tocitem target="curvefit_product_page.html" image="$toolbox/matlab/icons/pdficon.gif">Printable Documentation (PDF)</tocitem>
<tocitem target="http://www.mathworks.com/products/curvefitting/" image="$toolbox/matlab/icons/webicon.gif">Product Page (Web)</tocitem>

</tocitem>
</toc>
