<?xml version='1.0' encoding='ISO-8859-1'  ?>
<!-- $Revision: 1.1.6.8 $ $Date: 2004/04/26 23:37:04 $ -->

<index version="1.0">
<indexitem target="text.html#19023">% &lt;VariableName&gt; notation</indexitem>
<indexitem target="gettin13.html#7506">activating components in a setup file</indexitem>
<indexitem target="gettin11.html#7469">adding components to a setup file</indexitem>
<indexitem target="axesloop.html#173554">Axes Loop</indexitem>
<indexitem target="axessnapshot.html#173579">Axes Snapshot</indexitem>
<indexitem target="blockexecutionorderlist.html#187755">Block Execution Order</indexitem>
<indexitem target="blockloop.html#191555">Block Loop</indexitem>
<indexitem target="blocktypecount.html#225789">Block Type Count</indexitem>
<indexitem target="bus.html#191592">Bus</indexitem>
<indexitem target="chaptersubsection.html#196393">Chapter/Subsection</indexitem>
<indexitem target="chartloop.html#196435">Chart Loop</indexitem>
<indexitem>command line
    <indexitem target="getting6.html#8522">generating reports</indexitem>
</indexitem>
<indexitem target="comment.html#196471">Comment</indexitem>
<indexitem>components
    <indexitem target="gettin13.html#7506">activating</indexitem>
    <indexitem target="gettin11.html#7469">adding</indexitem>
    <indexitem target="gettin13.html#7506">deactivating</indexitem>
    <indexitem target="gettin13.html#7488">deleting</indexitem>
    <indexitem target="getting3.html#7333">description</indexitem>
    <indexitem target="ref_in12.html#7457">Fixed-Point components</indexitem>
    <indexitem target="ref_int6.html#6666">Handle Graphics components</indexitem>
    <indexitem target="ref_int5.html#6766">Logic and Flow components</indexitem>
    <indexitem target="ref_int7.html#6897">MATLAB components</indexitem>
    <indexitem target="ref_int8.html#6461">Requirements Management Inferface components</indexitem>
    <indexitem target="ref_in10.html#12728">Simulink Blocks components</indexitem>
    <indexitem target="ref_int9.html#7003">Simulink components</indexitem>
    <indexitem target="ref_in11.html#7308">Stateflow components</indexitem>
</indexitem>
<indexitem target="genera10.html#9176">converting XML documents</indexitem>
<indexitem target="gettin13.html#7506">deactivating components in a setup file</indexitem>
<indexitem target="gettin13.html#7488">deleting components</indexitem>
<indexitem target="generat5.html#6313">DocBook SGML report</indexitem>
<indexitem target="documentation.html#233652">Documentation</indexitem>
<indexitem target="emptycomponent.html#196505">Empty Component</indexitem>
<indexitem target="evaluatematlabexpression.html#196537">Evaluate MATLAB Expression</indexitem>
<indexitem target="figureloop.html#196585">Figure Loop</indexitem>
<indexitem target="figuresnapshot.html#196627">Figure Snapshot</indexitem>
<indexitem target="fixedpointblockloop.html#15343">Fixed-Point Block Loop</indexitem>
<indexitem target="ref_in12.html#7457">Fixed-Point components</indexitem>
<indexitem target="fixedpointloggingoptions.html#196705">Fixed-Point Logging Options</indexitem>
<indexitem target="fixedpointpropertytable.html#196746">Fixed-Point Property Table</indexitem>
<indexitem target="fixedpointsummarytable.html#196783">Fixed-Point Summary Table</indexitem>
<indexitem target="generat5.html#6313">flow object tree (XML)</indexitem>
<indexitem target="forloop.html#196821">For Loop</indexitem>
<indexitem target="genera14.html#9365">generating M-code</indexitem>
<indexitem>generating reports
    <indexitem target="getting6.html#8522">using the command line</indexitem>
</indexitem>
<indexitem>Handle Graphics
    <indexitem target="ref_int6.html#6666">components</indexitem>
    <indexitem target="editing9.html#11487">figure property table</indexitem>
    <indexitem target="editing5.html#6127">HandleVisibility</indexitem>
    <indexitem target="editing5.html#6124">invisible figures</indexitem>
    <indexitem target="editing5.html#6139">tags</indexitem>
</indexitem>
<indexitem target="handlegraphicslinkinganchor.html#196862">Handle Graphics Linking Anchor</indexitem>
<indexitem target="handlegraphicsname.html#196899">Handle Graphics Name</indexitem>
<indexitem target="handlegraphicsobjectloop.html#196925">Handle Graphics Object Loop</indexitem>
<indexitem target="handlegraphicsparameter.html#196959">Handle Graphics Parameter</indexitem>
<indexitem target="handlegraphicspropertytable.html#197010">Handle Graphics Property Table</indexitem>
<indexitem target="handlegraphicssummarytable.html#197078">Handle Graphics Summary Table</indexitem>
<indexitem>HTML report
    <indexitem target="generat5.html#6313">stylesheets</indexitem>
</indexitem>
<indexitem target="image.html#197123">Image</indexitem>
<indexitem target="importfile.html#197163">Import File</indexitem>
<indexitem target="insertvariable.html#197201">Insert Variable</indexitem>
<indexitem target="genera15.html#13216">legacy setup files</indexitem>
<indexitem target="link.html#197237">Link</indexitem>
<indexitem target="list.html#197272">List</indexitem>
<indexitem target="genera13.html#6561">log files</indexitem>
<indexitem target="ref_int5.html#6766">Logic and Flow components</indexitem>
<indexitem target="logicalelse.html#197308">Logical Else</indexitem>
<indexitem target="logicalelseif.html#197344">Logical Elseif</indexitem>
<indexitem target="logicalif.html#197380">Logical If</indexitem>
<indexitem target="logicalthen.html#197416">Logical Then</indexitem>
<indexitem target="lookuptable.html#237898">Look-Up Table</indexitem>
<indexitem target="machineloop.html#197461">Machine Loop</indexitem>
<indexitem target="ref_int7.html#6897">MATLAB components</indexitem>
<indexitem target="matlabpropertytable.html#197488">MATLAB Property Table</indexitem>
<indexitem target="matlabtoolboxversionnumber.html#197521">MATLAB/Toolbox Version Number</indexitem>
<indexitem target="generat5.html#6313">Microsoft Word report</indexitem>
<indexitem target="modelchangelog.html#197571">Model Change Log</indexitem>
<indexitem target="modelloop.html#197605">Model Loop</indexitem>
<indexitem target="modelsimulation.html#197639">Model Simulation</indexitem>
<indexitem target="nestsetupfile.html#197675">Nest Setup File</indexitem>
<indexitem target="paragraph.html#197767">Paragraph</indexitem>
<indexitem target="gettin17.html#8939">Preferences dialog box</indexitem>
<indexitem target="generat6.html#8195">printing report</indexitem>
<indexitem>property tables
    <indexitem target="editin15.html#6947">adding and deleting columns and rows</indexitem>
    <indexitem target="editin18.html#11026">creating custom tables</indexitem>
    <indexitem target="editin14.html#6942">displaying or hiding table and cell borders</indexitem>
    <indexitem target="editin12.html#6905">editing the table title</indexitem>
    <indexitem target="editin13.html#6917">modifying properties in a table</indexitem>
    <indexitem target="editin10.html#6364">property name/property value pairs</indexitem>
    <indexitem target="editin11.html#6876">putting text into a table cell</indexitem>
</indexitem>
<indexitem target="getting6.html#8522">report</indexitem>
<indexitem>Report Generator
    <indexitem target="getting4.html#8491">generating a report</indexitem>
    <indexitem target="getting3.html#9998">overview</indexitem>
</indexitem>
<indexitem>reports
    <indexitem target="getting3.html#6137">description</indexitem>
    <indexitem target="generat9.html#6480">description field in report options</indexitem>
    <indexitem target="getting4.html#8491">generating</indexitem>
    <indexitem target="getting6.html#8522">generating from command line</indexitem>
    <indexitem target="generat6.html#8195">printing</indexitem>
    <indexitem target="generat2.html#8754">setting output options</indexitem>
    <indexitem target="generat3.html#6251">setting report file directory</indexitem>
    <indexitem target="generat4.html#6281">setting the report filename</indexitem>
    <indexitem target="generat5.html#6310">setting the report format</indexitem>
    <indexitem target="generat6.html#8040">viewing and printing</indexitem>
</indexitem>
<indexitem target="ref_int8.html#6461">Requirements Management Interface components</indexitem>
<indexitem target="requirementstable.html#197811">Requirements Table</indexitem>
<indexitem target="generat5.html#6313">rich text format</indexitem>
<indexitem target="scopesnapshot.html#241929">Scope Snapshot</indexitem>
<indexitem target="gettin16.html#9538">sending objects to MATLAB workspace</indexitem>
<indexitem>setup file
    <indexitem target="generat7.html#6461">autosaving on report generation</indexitem>
</indexitem>
<indexitem target="generat5.html#6313">SGML report</indexitem>
<indexitem target="signalloop.html#246299">Signal Loop</indexitem>
<indexitem target="simulinkautomatictable.html#197888">Simulink Automatic Table</indexitem>
<indexitem target="ref_in10.html#12728">Simulink Blocks components</indexitem>
<indexitem target="ref_int9.html#7003">Simulink components</indexitem>
<indexitem target="simulinkfunctionsandvariables.html#197923">Simulink Functions and Variables</indexitem>
<indexitem target="simulinklinkinganchor.html#199342">Simulink Linking Anchor</indexitem>
<indexitem target="simulinkname.html#199378">Simulink Name</indexitem>
<indexitem target="simulinkproperty.html#35660">Simulink Property</indexitem>
<indexitem target="simulinkpropertytable.html#199429">Simulink Property Table</indexitem>
<indexitem target="simulinksummarytable.html#199481">Simulink Summary Table</indexitem>
<indexitem target="stateloop.html#200652">State Loop</indexitem>
<indexitem target="stateflowautomatictable.html#200678">Stateflow Automatic Table</indexitem>
<indexitem target="ref_in11.html#7308">Stateflow components</indexitem>
<indexitem target="stateflowcount.html#220713">Stateflow Count</indexitem>
<indexitem target="stateflowfilter.html#216909">Stateflow Filter</indexitem>
<indexitem target="stateflowhierarchy.html#221919">Stateflow Hierarchy</indexitem>
<indexitem target="stateflowhierarchyloop.html#200713">Stateflow Hierarchy Loop</indexitem>
<indexitem target="stateflowlinkinganchor.html#200748">Stateflow Linking Anchor</indexitem>
<indexitem target="stateflowname.html#200810">Stateflow Name</indexitem>
<indexitem target="stateflowobjectloop.html#200841">Stateflow Object Loop</indexitem>
<indexitem target="stateflowproperty.html#200868">Stateflow Property</indexitem>
<indexitem target="stateflowpropertytable.html#200903">Stateflow Property Table</indexitem>
<indexitem target="stateflowsnapshot.html#200939">Stateflow Snapshot</indexitem>
<indexitem target="stateflowsummarytable.html#200983">Stateflow Summary Table</indexitem>
<indexitem target="stopreportgeneration.html#201017">Stop Report Generation</indexitem>
<indexitem target="generat5.html#6313">stylesheets</indexitem>
<indexitem target="systemfilter.html#201051">System Filter</indexitem>
<indexitem target="systemhierarchy.html#201108">System Hierarchy</indexitem>
<indexitem target="systemloop.html#201143">System Loop</indexitem>
<indexitem target="systemsnapshot.html#201181">System Snapshot</indexitem>
<indexitem target="table.html#201218">Table</indexitem>
<indexitem target="text.html#201254">Text</indexitem>
<indexitem target="timedatestamp.html#201290">Time/Date Stamp</indexitem>
<indexitem target="titlepage.html#201326">Title Page</indexitem>
<indexitem target="toworkspaceplot.html#229978">To Workspace Plot</indexitem>
<indexitem target="truthtable.html#201354">Truth Table</indexitem>
<indexitem target="gettin15.html#8871">variable notation</indexitem>
<indexitem target="variabletable.html#201390">Variable Table</indexitem>
<indexitem>viewing report
    <indexitem target="generat6.html#8040">after generating report</indexitem>
</indexitem>
<indexitem target="generat5.html#6313">Web stylesheet</indexitem>
<indexitem target="whileloop.html#201429">While Loop</indexitem>
<indexitem target="generat5.html#6313">XML report</indexitem>

</index>
